[
  {
  "id": 1,
  "logo": "https://example.com/nsu-logo.png",
  "name": "North South University (NSU)",
  "establishment": "1992",
  "iebCertified": true,
  "session": "Summer 2025",
  "hscBatch": "2022-2024",
  "examDate": "March 18, 2025",
  "courses": [
    { "name": "Computer Science and Engineering (CSE)", "cost": "7,60,000 BDT", "credits": "144" },
    { "name": "Electrical and Electronics Engineering (EEE)", "cost": "7,20,000 BDT", "credits": "140" },
    { "name": "Business Administration (BBA)", "cost": "6,70,000 BDT", "credits": "135" },
    { "name": "Economics", "cost": "6,40,000 BDT", "credits": "130" },
    { "name": "Environmental Science", "cost": "6,10,000 BDT", "credits": "128" },
    { "name": "Pharmacy", "cost": "8,30,000 BDT", "credits": "160" },
    { "name": "English", "cost": "5,90,000 BDT", "credits": "120" },
    { "name": "Political Science", "cost": "6,00,000 BDT", "credits": "125" },
    { "name": "Biochemistry", "cost": "6,50,000 BDT", "credits": "130" },
    { "name": "Mathematics", "cost": "5,80,000 BDT", "credits": "120" }
  ]
},
  {
    "id": 2,
    "logo": "https://example.com/brac-logo.png",
    "name": "BRAC University",
    "establishment": "2001",
    "iebCertified": true,
    "session": "Summer 2025",
    "hscBatch": "2022-2024",
    "examDate": "March 15, 2025",
    "courses": [
      { "name": "Computer Science and Engineering (CSE)", "cost": "7,50,000 BDT", "credits": "140" },
      { "name": "Business Administration (BBA)", "cost": "6,80,000 BDT", "credits": "130" },
      { "name": "Economics", "cost": "6,50,000 BDT", "credits": "128" },
      { "name": "Architecture", "cost": "8,00,000 BDT", "credits": "160" },
      { "name": "Microbiology", "cost": "6,20,000 BDT", "credits": "125" },
      { "name": "English", "cost": "5,80,000 BDT", "credits": "120" },
      { "name": "Law", "cost": "7,00,000 BDT", "credits": "135" },
      { "name": "Pharmacy", "cost": "8,50,000 BDT", "credits": "165" },
      { "name": "Environmental Science", "cost": "6,00,000 BDT", "credits": "130" },
      { "name": "Anthropology", "cost": "5,50,000 BDT", "credits": "120" }
    ]
  },
  {
    "id": 3,
    "logo": "https://example.com/aiub-logo.png",
    "name": "American International University-Bangladesh (AIUB)",
    "establishment": "1994",
    "iebCertified": true,
    "session": "Summer 2025",
    "hscBatch": "2022-2024",
    "examDate": "March 20, 2025",
    "courses": [
      { "name": "Computer Science and Engineering (CSE)", "cost": "7,20,000 BDT", "credits": "142" },
      { "name": "Electrical and Electronics Engineering (EEE)", "cost": "7,00,000 BDT", "credits": "140" },
      { "name": "Business Administration (BBA)", "cost": "6,50,000 BDT", "credits": "132" },
      { "name": "Computer Engineering (CE)", "cost": "7,10,000 BDT", "credits": "140" },
      { "name": "Telecommunication Engineering (TE)", "cost": "7,00,000 BDT", "credits": "138" },
      { "name": "Software Engineering (SWE)", "cost": "7,30,000 BDT", "credits": "145" },
      { "name": "Accounting", "cost": "6,40,000 BDT", "credits": "130" },
      { "name": "Marketing", "cost": "6,30,000 BDT", "credits": "128" },
      { "name": "Finance", "cost": "6,50,000 BDT", "credits": "130" },
      { "name": "Human Resource Management (HRM)", "cost": "6,20,000 BDT", "credits": "125" }
    ]
  },
  
  {
    "id": 4,
    "logo": "https://example.com/iub-logo.png",
    "name": "Independent University, Bangladesh (IUB)",
    "establishment": "1993",
    "iebCertified": true,
    "session": "Summer 2025",
    "hscBatch": "2022-2024",
    "examDate": "March 22, 2025",
    "courses": [
      { "name": "Computer Science and Engineering (CSE)", "cost": "7,40,000 BDT", "credits": "142" },
      { "name": "Electrical and Electronics Engineering (EEE)", "cost": "7,10,000 BDT", "credits": "140" },
      { "name": "Business Administration (BBA)", "cost": "6,60,000 BDT", "credits": "132" },
      { "name": "Environmental Management", "cost": "6,20,000 BDT", "credits": "128" },
      { "name": "Media and Communication", "cost": "6,00,000 BDT", "credits": "125" },
      { "name": "Pharmacy", "cost": "8,20,000 BDT", "credits": "160" },
      { "name": "English", "cost": "5,90,000 BDT", "credits": "120" },
      { "name": "Anthropology", "cost": "5,80,000 BDT", "credits": "120" },
      { "name": "Public Health", "cost": "6,50,000 BDT", "credits": "130" },
      { "name": "Biotechnology", "cost": "6,30,000 BDT", "credits": "128" }
    ]
  },
  {
    "id": 5,
    "logo": "https://example.com/ewu-logo.png",
    "name": "East West University (EWU)",
    "establishment": "1996",
    "iebCertified": true,
    "session": "Summer 2025",
    "hscBatch": "2022-2024",
    "examDate": "March 25, 2025",
    "courses": [
      { "name": "Computer Science and Engineering (CSE)", "cost": "7,30,000 BDT", "credits": "140" },
      { "name": "Electrical and Electronics Engineering (EEE)", "cost": "7,00,000 BDT", "credits": "138" },
      { "name": "Business Administration (BBA)", "cost": "6,50,000 BDT", "credits": "130" },
      { "name": "Economics", "cost": "6,20,000 BDT", "credits": "128" },
      { "name": "English", "cost": "5,80,000 BDT", "credits": "120" },
      { "name": "Law", "cost": "6,90,000 BDT", "credits": "135" },
      { "name": "Pharmacy", "cost": "8,10,000 BDT", "credits": "160" },
      { "name": "Environmental Science", "cost": "6,00,000 BDT", "credits": "125" },
      { "name": "Mathematics", "cost": "5,70,000 BDT", "credits": "120" },
      { "name": "Sociology", "cost": "5,90,000 BDT", "credits": "120" }
    ]
  }
]